LICENSE
README.md
setup.py
cnforpy/__init__.py
cnforpy/main.py
cnforpy/version.py
cnforpy.egg-info/PKG-INFO
cnforpy.egg-info/SOURCES.txt
cnforpy.egg-info/dependency_links.txt
cnforpy.egg-info/entry_points.txt
cnforpy.egg-info/requires.txt
cnforpy.egg-info/top_level.txt