Metadata-Version: 2.1
Name: cnforpy
Version: 1.0.1
Summary: 一个中文编程语言
Home-page: https://heikeling.github.io
Author: Leaves-Technology
Author-email: rainwang_20220102@163.com
Maintainer: Leaves-Technology
Maintainer-email: rainwang_20220102@163.com
License:                                  Apache License
Platform: UNKNOWN
Classifier: Environment :: Console
Classifier: Natural Language :: Chinese (Simplified)
Classifier: Programming Language :: Python
Classifier: Programming Language :: Python :: 3.6
Classifier: Programming Language :: Python :: 3.7
Classifier: Programming Language :: Python :: 3.8
Classifier: Programming Language :: Python :: 3.9
Classifier: Programming Language :: Python :: 3.10
Classifier: Programming Language :: Python :: 3.11
Classifier: Programming Language :: Python :: Implementation
Classifier: Programming Language :: Python :: Implementation :: CPython
Classifier: Programming Language :: Python :: Implementation :: PyPy
Classifier: Operating System :: OS Independent
Requires-Python: >=3.8
License-File: LICENSE
